SpecularLang/SpecLangErrorHandle.py
SpecularLang/SpecLangLexer.py
SpecularLang/SpecLangListener.py
SpecularLang/SpecLangParser.py
SpecularLang/SpecLangTypes.py
SpecularLang/SpecLangVisitor.py
SpecularLang/SpecLangWalker.py
SpecularLang/__init__.py
SpecularLang/compile.py
SpecularLang-1.1.1.dist-info/LICENSE
SpecularLang-1.1.1.dist-info/METADATA
SpecularLang-1.1.1.dist-info/WHEEL
SpecularLang-1.1.1.dist-info/entry_points.txt
SpecularLang-1.1.1.dist-info/top_level.txt
SpecularLang-1.1.1.dist-info/RECORD
